LICENSE
README.md
setup.py
GreenPy/__init__.py
GreenPy/algebra.py
GreenPy/green.py
GreenPy/library.py
GreenPy.egg-info/PKG-INFO
GreenPy.egg-info/SOURCES.txt
GreenPy.egg-info/dependency_links.txt
GreenPy.egg-info/not-zip-safe
GreenPy.egg-info/top_level.txt