Metadata-Version: 2.1
Name: GreenPy
Version: 0.1
Summary: Decimation of the Green function in graphene nanoribbons
Home-page: UNKNOWN
License: UNKNOWN
Platform: UNKNOWN
License-File: LICENSE
